clearfinder
