Metadata-Version: 1.0
Name: ClearFinder
Version: 0.1.2
Summary: Identify clear measurements from solar irradiation data
Home-page: UNKNOWN
Author: Philip Schleihauf
Author-email: uniphil@gmail.com
License: GPLv3
Platform: UNKNOWN
